pheed/__init__.py
pheed/core/__init__.py
pheed/core/article.py
pheed/core/author.py
pheed/core/source.py
pheed/core/tests/__init__.py
pheed/core/tests/test_article.py
pheed/core/tests/test_author.py
pheed/core/tests/test_source.py
pheed/sources/__init__.py
pheed/sources/aps.py
pheed/sources/arxiv.py
pheed/sources/iop.py
pheed-0.0.1.dist-info/LICENSE
pheed-0.0.1.dist-info/METADATA
pheed-0.0.1.dist-info/WHEEL
pheed-0.0.1.dist-info/top_level.txt
pheed-0.0.1.dist-info/RECORD
