Metadata-Version: 2.1
Name: pheed
Version: 0.0.1
Summary: Python tools for aggregating physics literature
Home-page: http://github.com/JWKennington/pheed
Author: James W. Kennington
Author-email: jameswkennington@gmail.com
License: MIT
Platform: UNKNOWN
